scraper/.DS_Store
scraper/__init__.py
scraper/article.py
scraper/cli.py
scraper/configuration.py
scraper/content_extractor.py
scraper/document_cleaner.py
scraper/image_extractor.py
scraper/named_entity_recognition.py
scraper/network.py
scraper/output_formatter.py
scraper/parser.py
scraper/patterns.py
scraper/settings.py
scraper/text.py
scraper/urls.py
scraper/utils.py
scraper/version.py
scraper/video_extractor.py
tests/__init__.py
tests/conftest.py
tests/mthreading.py
tests/fixtures/fulltext_domain_list.txt
tests/fixtures/html/247wallst.com1.html
tests/fixtures/html/247wallst.com2.html
tests/fixtures/html/Oxford_University_Press.html
tests/fixtures/html/about.com1.html
tests/fixtures/html/about.com2.html
tests/fixtures/html/adoption.com1.html
tests/fixtures/html/al.com1.html
tests/fixtures/html/al.com2.html
tests/fixtures/html/ap_meta_refresh.html
tests/fixtures/html/apartmenttherapy.com1.html
tests/fixtures/html/apartmenttherapy.com2.html
tests/fixtures/html/arabic_article.html
tests/fixtures/html/architecturaldigest.com1.html
tests/fixtures/html/architecturaldigest.com2.html
tests/fixtures/html/avclub.com1.html
tests/fixtures/html/avclub.com2.html
tests/fixtures/html/backstage.com1.html
tests/fixtures/html/backstage.com2.html
tests/fixtures/html/bhg.com1.html
tests/fixtures/html/bhg.com2.html
tests/fixtures/html/bloomberg.com1.html
tests/fixtures/html/books.google.com.html
tests/fixtures/html/bostonherald.com1.html
tests/fixtures/html/bostonherald.com2.html
tests/fixtures/html/businessinsider.com1.html
tests/fixtures/html/businessinsider.com2.html
tests/fixtures/html/businessweek.com1.html
tests/fixtures/html/businessweek.com2.html
tests/fixtures/html/chinese_article.html
tests/fixtures/html/cleveland.com1.html
tests/fixtures/html/cleveland.com2.html
tests/fixtures/html/cnn_article.html
tests/fixtures/html/cnn_main_site.html
tests/fixtures/html/cntraveler.com1.html
tests/fixtures/html/cntraveler.com2.html
tests/fixtures/html/coolhunting.com1.html
stimson_web_scraper-0.0.63.dist-info/LICENSE
stimson_web_scraper-0.0.63.dist-info/METADATA
stimson_web_scraper-0.0.63.dist-info/WHEEL
stimson_web_scraper-0.0.63.dist-info/entry_points.txt
stimson_web_scraper-0.0.63.dist-info/top_level.txt
stimson_web_scraper-0.0.63.dist-info/RECORD
