Metadata-Version: 2.1
Name: stimson-web-scraper
Version: 0.0.63
Summary: website article / adobe pdf file discovery & extraction
Home-page: https://github.com/Stimson-Center/stimson-web-scraper
Author: Alan S. Cooper
Author-email: cooper@pobox.com
License: MIT
Platform: UNKNOWN
Classifier: Programming Language :: Python :: 3
Classifier: License :: OSI Approved :: MIT License
Classifier: Natural Language :: English
Classifier: Intended Audience :: Developers
Classifier: Operating System :: OS Independent
Requires-Python: >=3.6
Requires-Dist: beautifulsoup4 (>=4.9.1)
Requires-Dist: click (>=7.1.2)
Requires-Dist: cssselect (>=1.1.0)
Requires-Dist: date-extractor (>=5.1.2)
Requires-Dist: fake-useragent (>=0.1.11)
Requires-Dist: feedfinder2 (>=0.0.4)
Requires-Dist: feedparser (>=5.2.1)
Requires-Dist: fpdf2 (>=2.0.5)
Requires-Dist: jieba3k (>=0.35.1)
Requires-Dist: lxml (>=4.5.2)
Requires-Dist: numpy (>=1.19.1)
Requires-Dist: pandas (>=1.1.0)
Requires-Dist: pdftotext (>=2.1.4)
Requires-Dist: Pillow (==6.2.2)
Requires-Dist: psutil (>=5.7.2)
Requires-Dist: pyarabic (>=0.6.8)
Requires-Dist: pytextrank (>=2.0.2)
Requires-Dist: pythainlp (>=2.2.2)
Requires-Dist: python-dateutil (>=2.8.1)
Requires-Dist: dateparser (>=0.7.6)
Requires-Dist: PyPDF4 (>=1.27.0)
Requires-Dist: PyYAML (>=5.3.1)
Requires-Dist: requests (>=2.24.0)
Requires-Dist: requests-toolbelt (>=0.9.1)
Requires-Dist: spacy (>=2.3.2)
Requires-Dist: tldextract (>=2.2.2)
Requires-Dist: tinysegmenter (==0.4)
Requires-Dist: waitress (>=1.4.4)
